getgpu/__init__.py
getgpu/get_idle.py
getgpu/get_idle_v2.py
getgpu/gpuinfo.py
getgpu-0.1.18.dist-info/LICENSE
getgpu-0.1.18.dist-info/METADATA
getgpu-0.1.18.dist-info/WHEEL
getgpu-0.1.18.dist-info/top_level.txt
getgpu-0.1.18.dist-info/RECORD
